{"stats":{"minecraft:custom":{"minecraft:time_since_rest":17861,"minecraft:crouch_one_cm":173,"minecraft:play_time":17861,"minecraft:walk_one_cm":2685,"minecraft:sneak_time":927,"minecraft:aviate_one_cm":199,"minecraft:jump":7,"minecraft:leave_game":1,"minecraft:time_since_death":17861,"minecraft:total_world_time":18106,"minecraft:fly_one_cm":211951},"minecraft:used":{"minecraft:stone_brick_stairs":25,"minecraft:stone_bricks":37,"minecraft:stone_brick_slab":10,"minecraft:deepslate_diamond_ore":18,"minecraft:diamond_block":3,"minecraft:sea_lantern":6,"minecraft:glowstone":6,"minecraft:prismarine_brick_slab":39,"minecraft:light_gray_concrete":1,"minecraft:warped_hyphae":18,"minecraft:prismarine_bricks":347,"minecraft:prismarine_brick_stairs":44,"minecraft:andesite":18,"minecraft:stone_stairs":51,"minecraft:gold_block":6,"minecraft:stone_slab":20,"minecraft:stone":83}},"DataVersion":3465}